aerotrace/__init__.py
aerotrace/models/__init__.py
aerotrace/models/engine.py
aerotrace/parsers/__init__.py
aerotrace/parsers/cgr30p.py
aerotrace_parsers-0.3.0.dist-info/METADATA
aerotrace_parsers-0.3.0.dist-info/WHEEL
aerotrace_parsers-0.3.0.dist-info/licenses/LICENSE
aerotrace_parsers-0.3.0.dist-info/RECORD
