Metadata-Version: 2.4
Name: aerotrace-parsers
Version: 0.3.0
Summary: Aircraft Engine Monitoring System (EMS) data parsers for real-time telemetry processing
Project-URL: Homepage, https://github.com/alexc/aerotrace-parsers
Project-URL: Repository, https://github.com/alexc/aerotrace-parsers
Project-URL: Issues, https://github.com/alexc/aerotrace-parsers/issues
Author-email: Alex Cartwright <alex@gewok.co.uk>
License: MIT
License-File: LICENSE
Keywords: aircraft,aviation,cgr30p,ems,engine,telemetry
Classifier: Development Status :: 4 - Beta
Classifier: Intended Audience :: Developers
Classifier: License :: OSI Approved :: MIT License
Classifier: Programming Language :: Python :: 3
Classifier: Programming Language :: Python :: 3.9
Classifier: Programming Language :: Python :: 3.10
Classifier: Programming Language :: Python :: 3.11
Classifier: Programming Language :: Python :: 3.12
Classifier: Topic :: Scientific/Engineering
Classifier: Topic :: System :: Monitoring
Requires-Python: >=3.9
Provides-Extra: dev
Requires-Dist: pytest-cov>=5.0; extra == 'dev'
Requires-Dist: pytest>=8.0; extra == 'dev'
Requires-Dist: ruff>=0.6.0; extra == 'dev'
